hack4u/Cur.py
hack4u/__init__.py
hack4u/utiles.py
hack4u_cursos-0.0.1.dist-info/METADATA
hack4u_cursos-0.0.1.dist-info/WHEEL
hack4u_cursos-0.0.1.dist-info/top_level.txt
hack4u_cursos-0.0.1.dist-info/RECORD
