Metadata-Version: 2.4
Name: hack4u-cursos
Version: 0.0.1
Summary: Biblioteca de hack4u para listar y buscar cursos.
Home-page: https://hack4u.io/
Author: Inaki Sobera
Classifier: Programming Language :: Python :: 3
Classifier: License :: OSI Approved :: MIT License
Classifier: Operating System :: OS Independent
Requires-Python: >=3.7
Dynamic: author
Dynamic: classifier
Dynamic: description
Dynamic: description-content-type
Dynamic: home-page
Dynamic: requires-python
Dynamic: summary
